{
  "h": {
    "c": 0,
    "e": "",
    "s": 1781508903,
    "t": 37,
    "apm": "5c94f20040ad910"
  },
  "c": {
    "author": {
      "nickname": "深圳大冲",
      "avatar": "https://pic-cdn.trytalks.com/pic/202503031212/avatar_19f14b0b4000cc54.jpg"
    },
    "note": {
      "topics": [],
      "book_topics": [],
      "post": {
        "follow_id": 0
      },
      "id": "1912601668372592768",
      "note_id": "1912601668372592768",
      "source": "app",
      "entry_type": "ai",
      "note_type": "class_audio",
      "title": "商业创业能力打造：第一性原理的应用方法分享",
      "json_content": "",
      "content": "### 📑 智能总结\n\n#### 课程信息\n- **授课时间**：2026-06-12 14:25:18\n- **时长**：59 分钟\n- **领域**：商业创业 / 商业思维能力训练\n\n#### 知识精讲\n本次课程围绕创业商业能力训练展开，结合学员项目点评讲解了战略定位选择，系统讲解了第一性原理的底层逻辑、落地步骤与跨场景应用，并介绍了MVP最小可行产品的验证方法。\n\n**AI创业项目战略定位点评**\n* **业务侧重选择**：AI相关创业需要明确业务侧重，要么以培训为主、企业商单为辅，要么以企业商单为主，不能同时发力多赛道，建议营收比例有清晰侧重，如8:2或7:3。\n   - 🚩重点：战略模糊会导致业务无法突破增长瓶颈，最终干不下去；战略清晰才能快速做大。\n   - 🚩重点：国内当前阶段优先做培训，海外优先做服务，半年到一年的千万级目标需要明确战略中心，边缘机会不能抢占核心资源。\n* **增长飞轮逻辑**：个人IP起盘获客，C端培训积累企业用户，企业用户后续反哺业务，形成正向增长飞轮。\n* **企业商单模式要求**：走企业商单路线需要联动商会、企业家俱乐部等资源，出海需要提前在Twitter/X等平台搭建自营曝光渠道。\n* **农下AI剪辑项目点评**：该AI剪辑产品基于大模型做语义视频组装，解决传统混剪低效问题，分三个定价版本：个人365元/年（按算力额外付费）、中小企业版、私有部署版（客单价2-3万），采用合伙人分销模式，合伙人获客利润归己，可联合拿大单。\n   - 🚩重点：分销驱动模式的核心风险是分销机制设计，需要筛选核心合伙人，工作室矩阵模式如果只收学费会培养对手，抽成会培养仇人，存在长期风险。\n\n**第一性原理核心讲解**\n* **定义与本质**：第一性原理最早由亚里士多德提出，核心是不接受现成答案和现象本身，只接受经过自己推导验证的底层逻辑和基础事实，区别于经验主义沿用旧结构旧假设，第一性原理会拆掉原有假设，从出发点重新思考。\n   - 🚩重点：掌握第一性原理就能超过99.9%的人，是所有商业决策、个人成长的核心底层能力。\n* **适用场景**：创业与商业抉择、学习与考试、产品设计与流程优化、个人成长与习惯养成。\n* **核心落地步骤**：\n   1. **系统化拆解**：系统定义为 $\\text{系统} = 要素 \\times 连接关系 \\times 环境$，任何复杂问题本质都是系统问题，拆解到不可再分的最小单元，直到直觉能给出答案为止。\n      - 训练方法：从简单物品（电脑、矿泉水瓶）开始训练拆解能力，再拆解抽象商业流程。\n   2. **质疑一切**：不是做杠精，而是跳出现有结构，质疑现有流程、规则、默认设计，围绕「是否必要、是否产生核心价值」两个问题判断，用结果导向而非过程完整性做标准。\n      - 🚩重点：典型误区：为了完整性增加无效复杂度，把看起来专业当成真实有用，必须回归结果导向。\n   3. **去芜存菁，系统重构**：拆解质疑后，保留最小可行核心结构，删除所有非必要部分，真正有效的战略只有一两个核心点。\n      - 判断标准：用ROI（投入产出比）衡量，核心标准为「是否值得，是否长期整体最优」，不需要追求完美。\n   4. **逐项优化**：同时优化多个模块会导致资源分散、无法做MVP验证，每个阶段只解决一个关键问题，永远优先优化ROI最高的模块，其他模块保持不变。\n   5. **加快周转（放量）**：前三步完成、系统验证为最优结构后再加快周转，本质是给已经优化的系统加杠杆，提升频率、放大规模。\n      - 🚩重点：系统未稳定前加速会放大所有问题，可能导致ROI由正转负、口碑崩塌。\n   6. **系统自动化**：系统高度结构化、决策逻辑验证完成后，实现低干预/无干预自动运行，AI是最终的放大器，不能拯救错误的系统，只能加速正确的系统。\n* **跨场景应用案例**：\n   - **高考提分案例**：四个月从400分提分到600+，没有从头补知识点，而是用第一性原理拆解高考系统，发现考试本身存在可利用的规律，比如英语作文全是议论文，套用蝴蝶效应排比框架即可快速写出满分作文；阅读理解日期题用「before加、after减」直接秒杀，最终放弃低投产比的内容，优先抓考试bug，实现快速提分。\n   - **马斯克造火箭案例**：马斯克拆解传统火箭2000多个零件，去芜存菁后整合为300多个一体化零件，成本降到原来的1/10，研发速度提升10倍，核心就是遵循「是否值得、是否长期整体最优」的判断标准。\n   - **AI破局社群案例**：用第一性原理拆解传统社群，质疑传统玩法后，保留核心交付：线上AI陪跑、线下AI实战、案例涌现、AI工具支撑四个核心模块，已经进入加快周转和自动化阶段，实现规模化增长。\n* **十倍增长结论**：设定10倍增长比设定2倍增长更容易成功，因为只有看似不可能的目标会倒逼你用第一性原理重新审视拆解系统，放弃非必要工作，集中资源打穿关键点。\n\n**MVP最小可行产品**\n* **定义**：MVP即最小可行产品，是低成本快速验证的产品迭代策略。\n* **经典案例**：Dropbox创始人在没有研发出产品的情况下，仅制作了产品功能演示视频发起众筹，获得5万美金预付款，后续融资后做出产品，最终以20亿美金卖给谷歌，是最经典的MVP实践。\n   - 🚩重点：MVP的核心是用最低成本最快速度验证需求，不需要先做出完美产品再启动。\n\n#### 📖 课堂实录\n[00:00:00](https://getnotes.seek:0) **AI创业业务战略点评开篇**\n业务模式必须有明确侧重，要么培训为主、企业商单为辅，要么专注企业商单，常见合理营收比例为8:2或7:3。\n\n[00:00:14](https://getnotes.seek:14) **彪悍起盘打法介绍**\n可以采用「个人IP+投流获客」的打法，对C端做AI流量操盘手/AI企业操盘手标品培训，客单价几千元，同时承接企业商单交付，收入以培训为主，这种模式和陈厂长的“手搓智能体”逻辑一致：个人IP起流量，C端业务养企业用户，后续企业用户反哺，形成增长飞轮，国内当前阶段这种模式增长更快。\n\n[00:01:46](https://getnotes.seek:106) **出海品牌模式要求**\n如果出海做企业家品牌，需要联动商会、地方企业家俱乐部资源，同时需要在Twitter/X搭建自营增长曝光渠道，如果没有这些准备，说明战略没有想清楚。\n\n[00:02:13](https://getnotes.seek:133) **战略模糊的危害**\n战略没想清楚，所有动作都是无效修补，业务做半年到一年就会干不下去；战略想清楚才能快速做大。当前国内优先做培训，海外优先做服务，同时做很难成功，未来半年要做千万营收，必须明确战略中心，不成熟的海外机会只是边缘机会，不能抢占核心资源。\n\n[00:03:24](https://getnotes.seek:204) **现阶段增长卡点分析**\n当前团队已经从小规模往体系增长跨不过去，核心就是战略定位模糊，动作都错了，核心优势（团队已经掌握IP全套打法、个人IP适配性好）没有发挥出来。\n\n[00:04:26](https://getnotes.seek:266) **新项目：农下AI剪品产品介绍**\n项目是基于AI驱动的语义视频组装工具，解决传统混剪工具生成低效的痛点，当前处于团队刚组建的阶段，打法为团队成员做个人IP，前期走免费流量，后续加投流。\n\n[00:05:12](https://getnotes.seek:312) **产品定价体系介绍**\n产品分三个版本：1.个人版：365元/年，用完额度后额外购买算力，面向自媒体从业者；2.中小企业版，面向中小企业和操盘手；3.私有部署版：客单价2-3万，面向需要数据本地化的大型企业。同时配套年度视频素材社群，后续发展合伙人模式，合伙人可自行获客，利润全部归自己，也可以联合拿大额企业订单。\n\n[00:06:15](https://getnotes.seek:375) **行业拓展计划**\n前期先切入1-2个行业，做透做出成功案例后再拓展其他行业，当前先做国内市场，开发多语言版本，后期从外贸、跨境电商客户切入，逐步拓展海外市场。\n\n[00:07:36](https://getnotes.seek:456) **项目模式风险提示**\n该项目采用合伙人分销模式，类似工作室矩阵加盟，如果产品力、销售力没有击穿市场，很容易卡住增长，这是需要注意的风险。\n\n[00:10:00](https://getnotes.seek:600) **课程开篇：商业发展的阶段卡点**\n事业每个阶段换挡，对应的底层商业逻辑完全不同，从副业到个体、团队、小规模、规模化、造血建壁垒，最终成为细分巨头，每个阶段逻辑都不同，哪怕做副业也要提前想清楚底层逻辑，可以边做边完善，但不能只盯着眼前赚钱，否则最终会走不下去。\n\n[00:11:09](https://getnotes.seek:669) **能力打造模块引入**\n前面已经讲了扫描行业、扫描自身、发挥优势、选择赛道、看到终局，接下来讲日常创业中如何训练自己的能力，底层能力支撑我们快速看到问题本质，持续做出高胜率选择。人生就是概率游戏，我们能做的只有加大胜率、降低败率，保证失败后不会彻底出局，核心就是提升底层能力。\n\n[00:13:15](https://getnotes.seek:795) **第一性原理定义引入**\n第一性原理最早由亚里士多德提出，核心是不满足于只看结果，追问结果产生的底层逻辑，是科学家、工程师长期使用的底层思维，本质是不接受现成答案和现象本身，只接受自己推导验证的底层逻辑和基础事实。第一性主义和经验主义的核心区别是：经验主义沿用旧结构旧假设，第一性原理拆掉假设，从出发点重新思考。\n\n[00:14:30](https://getnotes.seek:870) **第一性原理适用场景**\n适用核心场景包括：创业与商业抉择、学习与考试、产品设计与流程优化、个人成长与习惯养成。\n\n[00:14:35](https://getnotes.seek:875) **高考提分案例引入**\n老师自己高三三月统考只有400分，四个月目标提分200+考到600多分，常规思路是从头看书刷题，这个第一步就错了，没有用第一性原理思考：考600分不等于把所有知识点学会，考试本身是一个可以解码的系统，所以老师花了两周拆解高考题型规律，找考试可利用的规律。\n\n[00:16:30](https://getnotes.seek:990) **英语作文满分规律案例**\n拆解发现，非专八的所有英语考试作文全是议论文，都符合因果关系，可以套用蝴蝶效应的排比框架：“因为一颗马蹄钉，丢了一只马蹄铁；因为一只马蹄铁，输了一场战争；因为一场战争，亡了一个国家”，任何话题都可以套用这个框架，两分钟就能写出符合字数要求的满分作文。\n\n[00:19:24](https://getnotes.seek:1164) **英语阅读理解规律案例**\n拆解发现英语阅读理解日期题有固定规律：问到某件事在某个事件多久之前发生，直接用原日期做减法，之后直接得到答案，不需要读懂原文。\n\n[00:20:00](https://getnotes.seek:1200) **第一性原理核心逻辑总结**\n所有考试都有规律可寻，不需要按部就班从头学习，第一性原理就是不默认“必须这么做”，追问做这件事的核心目标，找到更高效的路径。放到商业中也是一样，做任何业务都要追问“我为什么做这件事，核心要拿到什么结果”，得到的答案和默认路径完全不同。\n\n[00:21:30](https://getnotes.seek:1290) **第一性原理落地步骤讲解**\n在马斯克提出的“质疑一切、去芜存菁、逐项优化、加快周转、系统自动化”基础上，补充了系统化拆解和质疑一切两步，因为大部分人没有系统化拆解能力，无法做到真正的质疑一切。以高考提分为例：先把考试拆解为“知识点掌握、心理素质、考试技巧、系统规律（bug）”四个要素，基础知识只占20%-30%，所以可以放弃大部分知识点，抓住后面三个模块就能拿到600分，最终实现目标。\n\n[00:24:35](https://getnotes.seek:1475) **系统的核心定义**\n系统公式：$$\\text{系统} = 要素 \\times 连接关系 \\times 环境$$，任何事物都是系统，哪怕一瓶矿泉水都可以拆解为瓶盖、瓶身、包装三个要素，连接关系为螺纹旋转、胶粘，适用环境为0-50℃，拆解后复杂问题就会变简单。\n\n[00:27:36](https://getnotes.seek:1656) **系统化拆解方法**\n将目标对象拆解到不可再拆的最小单元，判断标准：如果直觉不能给出答案，就需要继续拆解。拆解后还要梳理要素连接关系和环境对系统的影响，最终做成可视化的系统图。训练方法：从简单物品开始练习，逐步训练抽象商业问题的拆解能力。\n\n[00:29:59](https://getnotes.seek:1799) **质疑一切的核心逻辑**\n质疑一切不是做杠精，而是跳出现有结构，让你看到原本看不见的机会，质疑不是为了反对，而是为了打破原有思维局限。质疑对象包括现有流程、既定规则、默认设计，正确的质疑方法是围绕两个问题：这件事是否必要？是否产生核心价值？\n\n[00:32:00](https://getnotes.seek:1920) **工作室矩阵模式质疑案例**\n很多工作室矩阵模式收加盟费再抽10%分成，看似合理，本质有问题：加盟者学会后，没有约束机制能保证长期给你分成，大概率最后会脱离，所以只收学费是培养对手，抽成是培养仇人，长期走不通，不符合“长期整体最优”的标准。\n\n[00:35:04](https://getnotes.seek:2104) **去芜存菁系统重构**\n系统化拆解质疑后，重新计算最小可行结构，保留最小核心，删除其余所有部分，真正有用的战略只有一两个核心点，非常简单。大部分人都很忙，但很多忙都是非必要的，要定期反问自己：这件事需要做吗？能不能删掉？\n\n[00:38:00](https://getnotes.seek:2280) **系统重构判断标准**\n核心判断标准是ROI（投入产出比），不需要追求完美，只需要满足两点：是否值得，是否长期整体最优。马斯克造火箭案例：传统火箭有2000多个零件，马斯克拆解每个零件的作用后，将大部分零件一体化整合，最终只剩下300多个零件，成本降到原来的1/10，研发速度提升10倍，就是遵循这个标准。\n\n[00:40:25](https://getnotes.seek:2425) **逐项优化核心要点**\n必须逐项优化，同时优化多个模块会导致资源分散，没有参照组无法做MVP验证，甚至出错后无法回退。每次只改变一个变量，就能清楚看到这个改变对系统的影响，永远优先优化ROI最高的部分，每个阶段只解决一个关键问题，其他模块暂时保持不动。商业定位也是一样：增长卡点先拆解为流量侧、转化侧、产品侧，找到卡在哪一个模块，就聚焦解决这一个问题。\n\n[00:44:40](https://getnotes.seek:2680) **加快周转（放量）阶段要点**\n前三步完成，系统验证为最优结构后，才进入加快周转也就是放量阶段。放量的前提是转化率足够高、转化流程已经标准化，此时才能加杠杆放大规模，如果系统没做好就提前放量，会放大所有问题，最终导致项目失败。\n\n[00:47:17](https://getnotes.seek:2837) **系统自动化终极阶段**\n系统自动化就是员工甚至CEO都不再是系统运行的核心，系统可以在低干预/无干预下自动运行，前提是系统已经高度结构化，关键决策逻辑已经验证。AI是自动化阶段的放大器，AI只能加速正确的系统，无法拯救错误的系统。\n\n[00:48:15](https://getnotes.seek:2895) **第一性原理步骤复盘**\n完整步骤：1.用系统化思维看待问题，掌握系统化拆解能力；2.质疑一切现有默认规则；3.去芜存菁保留最小核心系统；4.逐项优化核心模块；5.验证完成后加快周转发量；6.最终实现系统自动化。这个逻辑适用于所有事情，从个人考试到创业公司都可以用。\n\n[00:49:49](https://getnotes.seek:2989) **破局社群应用案例**\n用第一性原理做AI破局社群，目标是成为中国头部AI社群，形成生态后切入AI产业链，拆解质疑传统社群玩法后，删除所有非必要交付，最终保留四个核心交付：线上AI陪跑、线下AI实战、案例涌现、全套AI工具支撑，围绕普通人AI转型从技能到链接到拿结果的核心需求，现在已经进入加快周转和自动化阶段。\n\n[00:52:45](https://getnotes.seek:3165) **跨场景应用总结**\n- 商业产品优化：不是全面升级，而是优先解决高权重模块，聚焦流量多转化低的节点、决策成本最高的流程、对收入影响最大的关键工作，找到转化漏斗的漏点优先解决。\n- 习惯养成：拆解习惯系统，重构不合理步骤，用微步骤+重复+监督加快周转。\n- 核心原则：追求整体最优而非局部最优，放弃看起来重要但不关键的部分，集中资源打穿关键点。\n\n[00:55:00](https://getnotes.seek:3300) **十倍增长结论**\n给自己设定10倍增长，比设定2倍增长更容易成功，因为10倍增长看起来不可能，会倒逼你用第一性原理重新审视拆解系统，放弃非必要工作，集中资源打穿关键点，最终会找到之前完全想不到的路径，所以可以定期给自己做极限挑战，倒逼思考。\n\n[00:56:46](https://getnotes.seek:3406) **MVP最小可行产品引入**\nMVP即最小可行产品，是低成本快速验证的产品迭代策略，经典案例是Dropbox：创始人在没有研发出产品的情况下，仅制作了产品功能演示视频放到众筹网站，预售一年使用权，最终众筹到5万美金，后续拿到融资做出产品，最终以20亿美金卖给谷歌，说明验证需求不需要先做出完美产品，用最低成本快速验证才是最高效的路径。\n\n### 🖍️ 重点速览\n\n#### 🚩 考点重点\n- [00:02:48](https://getnotes.seek:168) **业务战略定位**：必须明确单一战略中心，不能同时发力多赛道，战略模糊会导致无法突破增长瓶颈。\n- [00:15:28](https://getnotes.seek:928) **第一性原理核心**：掌握第一性原理就能超过99.9%的人，是所有商业决策的核心底层能力。\n- [00:33:19](https://getnotes.seek:1999) **工作室矩阵模式风险**：只收加盟费会培养对手，抽成会培养仇人，长期存在无法解决的风险。\n- [00:40:42](https://getnotes.seek:2442) **逐项优化原则**：每个阶段只解决一个关键问题，同时优化多个模块会导致无法验证效果。\n- [00:47:07](https://getnotes.seek:2827) **放量前置条件**：系统未验证稳定前不能提前放量，否则会放大所有问题，导致项目失败。\n- [00:47:48](https://getnotes.seek:2868) **AI定位**：AI只能加速正确的系统，无法拯救错误的系统，是放大器不是解决方法。\n- [00:55:24](https://getnotes.seek:3324) **十倍增长逻辑**：10倍增长比2倍增长更容易倒逼第一性原理思考，更容易成功。\n\n#### 💡 核心概念\n- **第一性原理**：不接受现成答案和现象本身，只接受经过自己推导验证的底层逻辑和基础事实，从出发点重新思考问题的思维方式。\n- **系统公式**：$$\\text{系统} = 要素 \\times 连接关系 \\times 环境$$\n- **MVP（最小可行产品）**：用最低成本快速验证需求的产品迭代策略，核心是先验证需求再做完整产品。\n\n#### ✨ 课堂金句\n- “人生就是一场概率游戏，我们所有能做的事情只有一件事：就是加大我胜率和降低我的败率，以及在失败的时候不至于一把被没收，到牌桌之下。”\n- “如果你始终是以赚钱的方式去做商业的话，那么走着走着就赚不到钱了。”\n- “设定10倍增长的确比设定两倍的增长更容易让你获得成功。”\n- “AI只能加速正确的系统，无法拯救错误的系统。”\n\n#### 📝 待办事项\n- **课堂作业**：用第一性原理拆解自身业务，回答第一性原理通用判断清单的问题\n- **阅读参考**：《增长黑客》",
      "body_text": "授课时间：2026-06-12 14:25:18<br>时长：59 分钟<br>领域：商业创业 / 商业思维能力训练<br>本次课程围绕创业商业能力训练展开，结合学员项目点评讲解了战略定位选择，系统讲解了第一性原理的底层逻辑、落地步骤与跨场景应用，并介绍了MVP最小可行产品的验证方法。<br>AI创业项目战略定位点评<br>业务侧重选择：AI相关创业需要明确业务侧重，要么以培训为主、企业商单为辅，要么以企业商单为主，不能同时发力多赛道，建议营收比例有清晰侧重，如8:2或7:3。<br>🚩重点：战略模糊会导致业务无法突破增长瓶颈，最终干不下去；战略清晰才能快速做大。<br>🚩重点：国内当前...",
      "ref_content": "",
      "res_info": {
        "title": "",
        "url": "",
        "ptype": 0,
        "ptype_cn_name": ""
      },
      "tags": [
        {
          "id": "290130701",
          "name": "录音笔记",
          "type": "system",
          "visible": true,
          "is_deleted": 0,
          "create_time": 1742623631,
          "update_time": 1781322023,
          "tag_type": "ai_audio"
        },
        {
          "id": "548396281",
          "name": "商业创业",
          "type": "ai",
          "visible": true,
          "is_deleted": 0,
          "create_time": 1781249286,
          "update_time": 1781249286,
          "tag_type": ""
        },
        {
          "id": "548396282",
          "name": "第一性原理",
          "type": "ai",
          "visible": true,
          "is_deleted": 0,
          "create_time": 1781249286,
          "update_time": 1781249286,
          "tag_type": ""
        },
        {
          "id": "548396283",
          "name": "战略规划",
          "type": "ai",
          "visible": true,
          "is_deleted": 0,
          "create_time": 1781249286,
          "update_time": 1781249286,
          "tag_type": ""
        }
      ],
      "is_ai_generated": true,
      "date_str": "",
      "attachments": [
        {
          "type": "audio",
          "url": "[redacted-media-url]",
          "size": 0,
          "title": "",
          "sub_title": "",
          "duration": 3552804
        }
      ],
      "relevant_questions": [],
      "audio_state": 0,
      "status": 0,
      "display_status": 0,
      "share_scope": 1,
      "share_exclude_audio": false,
      "share_id": "7gvWao4XZkzLL",
      "is_child_note": false,
      "parent_id": "",
      "small_images": [],
      "original_images": [],
      "has_ai_processed": true,
      "ai_error_type": "",
      "ai_error_reason": "",
      "edit_time": "2026-06-12 14:25:18",
      "created_at": "2026-06-12 14:25:18",
      "updated_at": "2026-06-12 16:32:30",
      "version": 1,
      "event_status": 0,
      "is_author": false,
      "is_in_topic": false,
      "is_in_book_topic": false,
      "client_note_id": "20260612-0625-8018-b873-6bada4238355",
      "can_append_note": false,
      "hide_source_entrance": false,
      "book": {
        "can_read_online": false,
        "chapter_name": "",
        "jump_url": ""
      },
      "timeline_version": 1,
      "prime_id": "9PWOW2rkG9Q86llP",
      "link_redirects": null,
      "tabs": [],
      "misc": ""
    },
    "already_saved": false,
    "url_with_acode": ""
  }
}
